testable_pytest/__init__.py
testable_pytest/client.py
testable_pytest/models.py
testable_pytest/plugin.py
testable_pytest/settings.py
testable_pytest-0.0.7.dist-info/METADATA
testable_pytest-0.0.7.dist-info/WHEEL
testable_pytest-0.0.7.dist-info/entry_points.txt
testable_pytest-0.0.7.dist-info/top_level.txt
testable_pytest-0.0.7.dist-info/RECORD
